aydie_genai/__init__.py
aydie_genai/constants.py
aydie_genai/exceptions.py
aydie_genai/genai.py
aydie_genai/utils.py
aydie_genai/providers/__init__.py
aydie_genai/providers/base_provider.py
aydie_genai/providers/claude_provider.py
aydie_genai/providers/deepseek_provider.py
aydie_genai/providers/gemini_provider.py
aydie_genai/providers/groq_provider.py
aydie_genai/providers/mistral_provider.py
aydie_genai/providers/openai_provider.py
aydie_genai-1.1.0.dist-info/licenses/LICENSE
tests/__init__.py
tests/test_genai.py
aydie_genai-1.1.0.dist-info/METADATA
aydie_genai-1.1.0.dist-info/WHEEL
aydie_genai-1.1.0.dist-info/top_level.txt
aydie_genai-1.1.0.dist-info/RECORD
