Metadata-Version: 2.4
Name: aydie_genai
Version: 1.1.0
Summary: A simple and unified Python library to interact with various Large Language Models (LLMs) like Gemini, GPT, Claude, and more by abstracting provider-specific code and authentication.
Home-page: https://github.com/aydiegithub/aydie-genai
Author: Aditya (Aydie) Dinesh K
Author-email: business@aydie.in
License: MIT
Project-URL: Bug Tracker, https://github.com/aydiegithub/aydie-genai/issues
Classifier: Programming Language :: Python :: 3
Classifier: License :: OSI Approved :: MIT License
Classifier: Operating System :: OS Independent
Classifier: Topic :: Scientific/Engineering :: Artificial Intelligence
Classifier: Intended Audience :: Developers
Classifier: Topic :: Software Development :: Libraries :: Python Modules
Requires-Python: >=3.9
License-File: LICENSE
Requires-Dist: google-generativeai
Requires-Dist: openai
Requires-Dist: anthropic
Requires-Dist: groq
Requires-Dist: deepseek
Requires-Dist: mistralai
Requires-Dist: python-dotenv
Dynamic: author
Dynamic: author-email
Dynamic: classifier
Dynamic: description
Dynamic: description-content-type
Dynamic: home-page
Dynamic: license
Dynamic: license-file
Dynamic: project-url
Dynamic: requires-dist
Dynamic: requires-python
Dynamic: summary
